mcp_vision_gateway/__init__.py
mcp_vision_gateway/__main__.py
mcp_vision_gateway-0.15.dist-info/licenses/LICENSE
mcp_vision_gateway-0.15.dist-info/METADATA
mcp_vision_gateway-0.15.dist-info/WHEEL
mcp_vision_gateway-0.15.dist-info/entry_points.txt
mcp_vision_gateway-0.15.dist-info/top_level.txt
mcp_vision_gateway-0.15.dist-info/RECORD
