Metadata-Version: 2.4
Name: mcp-vision-gateway
Version: 0.15
Summary: 连接MCP与视觉AI模型的网关服务，支持图像处理和纯文本对话
Home-page: https://github.com/yourusername/mcp-vision-gateway
Author: MCP Vision Gateway Authors
Author-email: your.email@example.com
Classifier: Programming Language :: Python :: 3
Classifier: License :: OSI Approved :: MIT License
Classifier: Operating System :: OS Independent
Classifier: Topic :: Software Development :: Libraries :: Python Modules
Classifier: Intended Audience :: Developers
Requires-Python: >=3.7
License-File: LICENSE
Requires-Dist: mcp>=1.6.0
Requires-Dist: requests>=2.25.0
Dynamic: author
Dynamic: author-email
Dynamic: classifier
Dynamic: description
Dynamic: description-content-type
Dynamic: home-page
Dynamic: license-file
Dynamic: requires-dist
Dynamic: requires-python
Dynamic: summary
